lambdata_z0li627/__init__.py
lambdata_z0li627/df_utils.py
lambdata_z0li627-0.0.1.dist-info/LICENSE
lambdata_z0li627-0.0.1.dist-info/METADATA
lambdata_z0li627-0.0.1.dist-info/WHEEL
lambdata_z0li627-0.0.1.dist-info/top_level.txt
lambdata_z0li627-0.0.1.dist-info/RECORD
