Metadata-Version: 2.1
Name: lambdata-z0li627
Version: 0.0.1
Summary: a collection of data science helper functions
Home-page: https://lambdaschool.com/courses/data-science
Author: z0li627
License: UNKNOWN
Platform: UNKNOWN
Classifier: Programming Language :: Python :: 3
Classifier: License :: OSI Approved :: MIT License
Classifier: Operating System :: OS Independent
Requires-Python: >=3.5
Requires-Dist: numpy
Requires-Dist: pandas
